{
  "instrument_key": "BINANCE:BTCUSDT:SPOT",
  "artifact_contract": {
    "schema_version": "v2",
    "mode": "live",
    "run_id": "ddc211624bf6474c907bcde362e0f624",
    "generated_at": "2026-03-26T05:03:06.679382+00:00",
    "window_end_ts": 1774501386679,
    "source": "live_engine"
  },
  "latest_tpfm": {
    "snapshot_id": "1355b7e2-350a-4252-aaf9-1b05b76f2dfb",
    "symbol": "BTCUSDT",
    "venue": "binance",
    "window_start_ts": 1774501033326,
    "window_end_ts": 1774501374814,
    "run_id": "ddc211624bf6474c907bcde362e0f624",
    "microprice": 70773.98480224566,
    "open_px": 70785.73,
    "high_px": 70803.85,
    "low_px": 70742.15,
    "close_px": 70773.98,
    "volume_quote": 1614516.2915389,
    "initiative_score": -0.47739781615692906,
    "initiative_polarity": "NEG_INIT",
    "initiative_strength": 0.47739781615692906,
    "inventory_score": 0.009596981834614377,
    "inventory_polarity": "NEUTRAL_INV",
    "inventory_strength": 0.009596981834614377,
    "axis_confidence": 0.81,
    "energy_score": 0.1214786763595781,
    "energy_state": "COMPRESSION",
    "response_efficiency_score": -0.03899585944500219,
    "response_efficiency_state": "MIXED",
    "conflict_score": 0.0,
    "agreement_score": 0.35,
    "tradability_score": 0.4312943006822014,
    "market_quality_score": 0.5635557995106291,
    "novelty_score": 0.8999999999999999,
    "matrix_cell": "NEG_INIT__NEUTRAL_INV",
    "micro_conclusion": "INITIATIVE_DRIVEN",
    "matrix_alias_vi": "Bán chủ động chưa có đè",
    "continuation_bias": "INITIATIVE_SELL_ONLY",
    "preferred_posture": "Theo dõi breakdown nhưng chưa đuổi, cần inventory xác nhận.",
    "tradability_grade": "C",
    "dominant_setups": [
      "stealth_accumulation",
      "breakout_ignition",
      "failed_breakout"
    ],
    "setup_score_map": {
      "stealth_accumulation": 70.0,
      "breakout_ignition": 66.0,
      "distribution": 52.0,
      "failed_breakout": 56.0
    },
    "active_thesis_count": 0,
    "new_thesis_count": 0,
    "actionable_count": 0,
    "invalidated_count": 4,
    "resolved_count": 0,
    "delta_quote": -584207.6135052999,
    "cvd_slope": -1710.7705497859365,
    "trade_burst": 4.205125802370801,
    "absorption_score": 3710595.390758743,
    "imbalance_l1": 0.5162267508399883,
    "centered_imbalance_l1": 0.032453501679976515,
    "signed_absorption_score": -1.0,
    "microprice_gap_bps": -0.0006785326078879237,
    "spread_bps": 0.001412868931646646,
    "delta_zscore": -0.5635949672017078,
    "aggression_ratio": 0.3190765814606758,
    "sweep_quote": 205400723.55071533,
    "sweep_buy_quote": 23856127.081387796,
    "sweep_sell_quote": 181544596.4693275,
    "burst_persistence": 0.7587769782660394,
    "microprice_drift_bps": -0.00026897182408048247,
    "replenishment_bid_score": 127116004.6076074,
    "replenishment_ask_score": 72415069.6611899,
    "context_score": 1.0,
    "basis_divergence": 0.0,
    "futures_bias_proxy": "SPOT_LED",
    "futures_context_available": true,
    "futures_context_fresh": true,
    "futures_delta_available": true,
    "futures_delta": -209853.86489999996,
    "funding_rate": 9.72e-06,
    "funding_bias": "NEUTRAL",
    "basis_bps": -4.135136243652662,
    "basis_divergence_state": "DIVERGING_NEG",
    "oi_value": 86768.828,
    "oi_delta": 0.5179999999963911,
    "oi_expansion_ratio": 5.969921507015535e-06,
    "oi_state": "EXPANDING",
    "futures_pressure_bias": "BEARISH",
    "futures_aggression_ratio": 0.3108421855662697,
    "spot_futures_relation": "SPOT_LED",
    "context_quality_score": 0.9789999999999999,
    "context_warning_flags": [],
    "basis_state": "DISCOUNT",
    "venue_confirmation_state": "CONFIRMED",
    "leader_venue": "binance",
    "lagger_venue": "bybit",
    "leader_confidence": 0.79,
    "aligned_window_ms": 14012,
    "venue_vwap_spread_bps": 0.8519377530515249,
    "liquidation_context_available": true,
    "liquidation_bias": "NONE",
    "liquidation_count": 0,
    "liquidation_quote": 0.0,
    "flow_state_code": "SELL_PRESSURE_BUILDUP",
    "forced_flow_state": "NONE",
    "forced_flow_intensity": 0.0,
    "liquidation_intensity": 0.0,
    "inventory_defense_state": "NONE",
    "transition_ready": true,
    "trap_risk": 0.0,
    "decision_posture": "WAIT",
    "decision_summary_vi": "Chỉ theo dõi, chờ thêm xác nhận từ futures hoặc đa sàn trước khi hành động.",
    "entry_condition_vi": "Inventory shift sang NEG_INV",
    "confirm_needed_vi": "Inventory flip NEG",
    "avoid_if_vi": "CVD futures phân kỳ dương",
    "review_tags": {
      "flow_state_code": "SELL_PRESSURE_BUILDUP",
      "matrix_cell": "NEG_INIT__NEUTRAL_INV",
      "continuation_bias": "INITIATIVE_SELL_ONLY",
      "spot_futures_relation": "SPOT_LED",
      "forced_flow_state": "NONE",
      "venue_confirmation_state": "CONFIRMED",
      "tradability_grade": "C",
      "basis_state": "DISCOUNT",
      "inventory_defense_state": "NONE",
      "transition_code": "INVENTORY_CONFIRM_TO_SHORT",
      "transition_family": "INVENTORY_CONFIRM"
    },
    "review_tags_json": "{\"flow_state_code\": \"SELL_PRESSURE_BUILDUP\", \"matrix_cell\": \"NEG_INIT__NEUTRAL_INV\", \"continuation_bias\": \"INITIATIVE_SELL_ONLY\", \"spot_futures_relation\": \"SPOT_LED\", \"forced_flow_state\": \"NONE\", \"venue_confirmation_state\": \"CONFIRMED\", \"tradability_grade\": \"C\", \"basis_state\": \"DISCOUNT\", \"inventory_defense_state\": \"NONE\", \"transition_code\": \"INVENTORY_CONFIRM_TO_SHORT\", \"transition_family\": \"INVENTORY_CONFIRM\"}",
    "entry_condition": "Inventory shift sang NEG_INV",
    "avoid_if": "CVD futures phân kỳ dương",
    "initiative_delta_1": -0.004902215774898133,
    "initiative_delta_3": -0.010586672620948756,
    "initiative_delta_5": -0.40146336938043653,
    "inventory_delta_1": -0.4004076905747675,
    "inventory_delta_3": -0.2669467310903399,
    "inventory_delta_5": -0.00922599972754262,
    "agreement_delta_3": -0.10000000000000002,
    "tradability_delta_3": -0.053780035322419095,
    "forced_flow_delta_3": 0.0,
    "tempo_state": "STABLE",
    "persistence_state": "EARLY",
    "exhaustion_risk": 0.0,
    "history_depth": 8,
    "sequence_id": "633cb5f2-f452-47f1-80c8-699af23185eb",
    "sequence_signature": "NEG_NEUTRALx1|STABLE|NONE|MIXED",
    "sequence_length": 1,
    "sequence_family": "SHORT",
    "sequence_quality": 0.32988702821034216,
    "pattern_code": "BREAKDOWN_FORMING_SHORT",
    "pattern_alias_vi": "Đang nén phá đáy Bán",
    "pattern_family": "NEG_INIT__NEUTRAL_INV",
    "pattern_phase": "FORMING",
    "pattern_strength": 0.27899826599718114,
    "pattern_quality": 0.4312943006822014,
    "pattern_failure_risk": 0.0,
    "sequence_start_ts": 1774501033326,
    "sequence_duration_sec": 341.488,
    "is_sequence_pivot": true,
    "edge_score": 0.45,
    "edge_confidence": "LOW",
    "historical_win_rate": 0.5,
    "expected_rr": 1.5,
    "parent_context": {
      "m30_regime": "UNKNOWN",
      "h4_structural_bias": "UNKNOWN",
      "m30_persistence": 0.0,
      "stack_alignment": "NEUTRAL"
    },
    "t_plus_1_price": 49997.613010919216,
    "t_plus_5_price": 49992.83903275765,
    "t_plus_12_price": 49988.065054596074,
    "degraded": false,
    "health_state": "HEALTHY",
    "blind_spot_flags": [],
    "should_escalate": true,
    "escalation_reason": [
      "Shift: NEG_INIT__POS_INV -> NEG_INIT__NEUTRAL_INV",
      "Inventory Flip: NEUTRAL_INV",
      "Futures Xác Nhận (Confluence)"
    ],
    "observed_facts": [
      "Delta spot -584.21K",
      "Nhịp 4.21/s",
      "Inventory L1 +3%",
      "Hấp thụ ký hiệu -1.00",
      "Sweep bán +205.40M | giữ lực 0.76",
      "Bid refill +127.12M",
      "Delta futures -209.85K | aggr 0.31"
    ],
    "inferred_facts": [
      "Bán chủ động chưa có đè",
      "Flow state: SELL_PRESSURE_BUILDUP",
      "Transition: Inventory xác nhận phe bán (INVENTORY_CONFIRM_TO_SHORT)",
      "INITIATIVE_DRIVEN",
      "Quan hệ spot/futures: SPOT_LED"
    ],
    "missing_context": [],
    "risk_flags": [],
    "action_plan_vi": "Chỉ theo dõi, chờ thêm xác nhận từ futures hoặc đa sàn trước khi hành động.",
    "flow_decision_brief": "☕ Đang theo dõi thị trường (Chờ chu kỳ nhận định tiếp theo)...",
    "invalid_if": "Dòng tiền bán nguội đi hoặc giá reclaim lại microprice.",
    "metadata": {
      "pattern_event": {
        "pattern_id": "cda905dd-4279-4143-9655-b8849a933a69",
        "snapshot_id": "1355b7e2-350a-4252-aaf9-1b05b76f2dfb",
        "symbol": "BTCUSDT",
        "venue": "binance",
        "timestamp": 1774501374814,
        "pattern_code": "BREAKDOWN_FORMING_SHORT",
        "pattern_alias_vi": "Đang nén phá đáy Bán",
        "pattern_family": "NEG_INIT__NEUTRAL_INV",
        "pattern_phase": "FORMING",
        "sequence_id": "633cb5f2-f452-47f1-80c8-699af23185eb",
        "sequence_signature": "NEG_NEUTRALx1|STABLE|NONE|MIXED",
        "sequence_length": 1,
        "tempo_state": "STABLE",
        "persistence_state": "EARLY",
        "pattern_strength": 0.27899826599718114,
        "pattern_quality": 0.4312943006822014,
        "pattern_failure_risk": 0.0,
        "matrix_cell": "NEG_INIT__NEUTRAL_INV",
        "flow_state_code": "NEUTRAL",
        "metadata": {
          "history_depth": 8
        }
      },
      "last_transition": {
        "transition_id": "f4fcee95-7461-4a24-9c85-59f1f26f1497",
        "symbol": "BTCUSDT",
        "venue": "binance",
        "timestamp": 1774501374814,
        "from_cell": "NEG_INIT__POS_INV",
        "to_cell": "NEG_INIT__NEUTRAL_INV",
        "transition_code": "INVENTORY_CONFIRM_TO_SHORT",
        "transition_speed": 1.0,
        "transition_quality": 0.76,
        "persistence_score": 1.0,
        "transition_family": "INVENTORY_CONFIRM",
        "transition_alias_vi": "Inventory xác nhận phe bán",
        "from_flow_state_code": "SHORT_TRAP_RISK",
        "to_flow_state_code": "NEUTRAL",
        "forced_flow_involved": false,
        "trap_risk": 0.0,
        "from_decision_posture": "WAIT",
        "to_decision_posture": "WAIT",
        "decision_shift": "HOLD_WAIT",
        "metadata": {
          "vNext": true,
          "from_flow_state_code": "SHORT_TRAP_RISK",
          "to_flow_state_code": "NEUTRAL",
          "from_grade": "C",
          "to_grade": "D",
          "from_spot_futures_relation": "SPOT_LED",
          "to_spot_futures_relation": "SPOT_LED"
        }
      },
      "decision_view": {
        "decision_id": "decision:1355b7e2-350a-4252-aaf9-1b05b76f2dfb",
        "snapshot_id": "1355b7e2-350a-4252-aaf9-1b05b76f2dfb",
        "symbol": "BTCUSDT",
        "venue": "binance",
        "timestamp": 1774501374814,
        "flow_bias": "SHORT",
        "continuation_bias": "INITIATIVE_SELL_ONLY",
        "posture": "WAIT",
        "tradability_grade": "C",
        "entry_condition": "Inventory shift sang NEG_INV",
        "confirm_needed": "Inventory flip NEG",
        "avoid_if": "CVD futures phân kỳ dương",
        "invalid_if": "Dòng tiền bán nguội đi hoặc giá reclaim lại microprice.",
        "tp_path": [
          "Chỉ theo dõi, chờ thêm xác nhận từ futures hoặc đa sàn trước khi hành động."
        ],
        "risk_flags": [],
        "review_tags": {
          "flow_state_code": "SELL_PRESSURE_BUILDUP",
          "matrix_cell": "NEG_INIT__NEUTRAL_INV",
          "continuation_bias": "INITIATIVE_SELL_ONLY",
          "spot_futures_relation": "SPOT_LED",
          "forced_flow_state": "NONE",
          "venue_confirmation_state": "CONFIRMED",
          "tradability_grade": "C",
          "basis_state": "DISCOUNT",
          "inventory_defense_state": "NONE",
          "transition_code": "INVENTORY_CONFIRM_TO_SHORT",
          "transition_family": "INVENTORY_CONFIRM"
        },
        "metadata": {}
      },
      "closed_sequence": {
        "sequence_id": "9ba190be-7e0d-42a0-9b4d-da77c2a7d7e9",
        "symbol": "BTCUSDT",
        "venue": "binance",
        "started_ts": 1774501033326,
        "ended_ts": 1774501361895,
        "sequence_signature": "NEG_INIT__POS_INV",
        "sequence_family": "SHORT",
        "sequence_length": 1,
        "sequence_bias": "SHORT",
        "sequence_strength": 0.4724956003820309,
        "sequence_maturity": "NEW",
        "sequence_quality": 0.46831945413917964,
        "stack_alignment_hint": "UNKNOWN",
        "current_cell": "NEG_INIT__POS_INV",
        "current_flow_state": "NEUTRAL",
        "resolution_hint": "BROKEN_BY_NEG_INIT__NEUTRAL_INV",
        "metadata": {
          "cumulative_initiative": -0.4724956003820309,
          "cumulative_inventory": 0.4100046724093819,
          "max_energy": 0.1328835991560211,
          "is_active": false
        }
      },
      "pattern_outcomes": [
        {
          "outcome_id": "234860a4-dc4c-47f7-91e2-8edf3e4ebeb3",
          "snapshot_id": "2a607b3b-cfc5-4806-91da-cb50b955f911",
          "symbol": "BTCUSDT",
          "timestamp": 1774500732793,
          "pattern_code": "PASSIVE_DISTRIBUTION",
          "sequence_signature": "NEUTRAL_NEGx1|DECELERATING|NONE|ABSORBED_OR_TRAP",
          "start_px": 70851.36797850278,
          "t1_px": 70776.74209280852,
          "t5_px": 70773.98480224566,
          "t12_px": 0.0,
          "r1_bps": -10.532737450729401,
          "r5_bps": -10.921902916623974,
          "r12_bps": 0.0,
          "max_favorable_bps": 3.6261856658879155,
          "max_adverse_bps": -15.41508394529827,
          "metadata": {}
        },
        {
          "outcome_id": "d846a908-25f2-4484-a9a5-c70264b12342",
          "snapshot_id": "dd3a80dd-2e7f-4645-a847-2f5a4cd1f79e",
          "symbol": "BTCUSDT",
          "timestamp": 1774501361895,
          "pattern_code": "TRAP_SHORT",
          "sequence_signature": "NEG_POSx1|STABLE|NONE|MIXED",
          "start_px": 70773.98090773656,
          "t1_px": 70773.98480224566,
          "t5_px": 0.0,
          "t12_px": 0.0,
          "r1_bps": 0.0005502741322217313,
          "r5_bps": 0.0,
          "r12_bps": 0.0,
          "max_favorable_bps": 4.220349326171126,
          "max_adverse_bps": -4.497543776443226,
          "metadata": {}
        }
      ]
    },
    "transition_event": {
      "transition_id": "f4fcee95-7461-4a24-9c85-59f1f26f1497",
      "symbol": "BTCUSDT",
      "venue": "binance",
      "timestamp": 1774501374814,
      "from_cell": "NEG_INIT__POS_INV",
      "to_cell": "NEG_INIT__NEUTRAL_INV",
      "transition_code": "INVENTORY_CONFIRM_TO_SHORT",
      "transition_speed": 1.0,
      "transition_quality": 0.76,
      "persistence_score": 1.0,
      "transition_family": "INVENTORY_CONFIRM",
      "transition_alias_vi": "Inventory xác nhận phe bán",
      "from_flow_state_code": "SHORT_TRAP_RISK",
      "to_flow_state_code": "NEUTRAL",
      "forced_flow_involved": false,
      "trap_risk": 0.0,
      "from_decision_posture": "WAIT",
      "to_decision_posture": "WAIT",
      "decision_shift": "HOLD_WAIT",
      "metadata": {
        "vNext": true,
        "from_flow_state_code": "SHORT_TRAP_RISK",
        "to_flow_state_code": "NEUTRAL",
        "from_grade": "C",
        "to_grade": "D",
        "from_spot_futures_relation": "SPOT_LED",
        "to_spot_futures_relation": "SPOT_LED"
      }
    },
    "stack_state": null,
    "edge_profile": {
      "setup_name": "BREAKDOWN_FORMING_SHORT",
      "historical_win_rate": 0.0,
      "expected_rr": 1.5,
      "sample_size": 20,
      "edge_score": 0.0,
      "confidence": "HIGH"
    }
  },
  "top_signals": [
    {
      "thesis_id": "7ae8b3d148a48c72",
      "instrument_key": "BINANCE:BTCUSDT:SPOT",
      "setup": "stealth_accumulation",
      "direction": "LONG_BIAS",
      "stage": "INVALIDATED",
      "score": 70.0,
      "confidence": 0.82,
      "coverage": 0.79,
      "why_now": [
        "Delta mua dương: 104231.75",
        "Bid L1 áp đảo: 0.87",
        "Nhịp trade tăng: 5.19/s",
        "Spread còn mỏng: 0.00 bps",
        "Hấp thụ chủ động cao: 108906.12"
      ],
      "conflicts": [
        "Giá khớp trượt dưới microprice",
        "Dòng tiền mới chỉ chiếm 17% cửa sổ, tín hiệu đã nguội.",
        "Cảnh báo: Sàn khác (okx) đang dẫn nhịp trước Binance."
      ],
      "invalidation": "Mất bid hỗ trợ dưới 70877.55",
      "entry_style": "Canh hồi về bid và giữ microprice",
      "targets": [
        "TP1: 1 ATR giả lập",
        "TP2: 2 ATR giả lập"
      ],
      "timeframe": "1h",
      "regime_bucket": "NEUTRAL",
      "flow_state": "SELL_PRESSURE_BUILDUP",
      "matrix_cell": "NEG_INIT__NEUTRAL_INV",
      "matrix_alias_vi": "Bán chủ động chưa có đè",
      "tradability_grade": "D",
      "decision_posture": "WAIT",
      "decision_summary_vi": "Chỉ theo dõi, chờ thêm xác nhận từ futures hoặc đa sàn trước khi hành động.",
      "flow_alignment_score": 0.0,
      "ai_brief_vi": "",
      "edge_score": 0.0,
      "edge_confidence": "HIGH",
      "pattern_code": "BREAKDOWN_FORMING_SHORT",
      "pattern_phase": "FORMING",
      "sequence_signature": "NEG_NEUTRALx1|STABLE|NONE|MIXED",
      "created_at": "2026-03-26T04:32:11.233000+00:00",
      "updated_at": "2026-03-26T04:32:37.039000+00:00",
      "metadata": {},
      "delta_score": 0.0,
      "prev_grade": "D",
      "grade_changed": false,
      "setup_changed": false,
      "prev_setup": "stealth_accumulation",
      "window_ts": 1774501386679
    }
  ],
  "m5_signal_history": [
    {
      "thesis_id": "7ae8b3d148a48c72",
      "instrument_key": "BINANCE:BTCUSDT:SPOT",
      "setup": "stealth_accumulation",
      "direction": "LONG_BIAS",
      "stage": "INVALIDATED",
      "score": 70.0,
      "confidence": 0.82,
      "coverage": 0.79,
      "why_now": [
        "Delta mua dương: 104231.75",
        "Bid L1 áp đảo: 0.87",
        "Nhịp trade tăng: 5.19/s",
        "Spread còn mỏng: 0.00 bps",
        "Hấp thụ chủ động cao: 108906.12"
      ],
      "conflicts": [
        "Giá khớp trượt dưới microprice",
        "Dòng tiền mới chỉ chiếm 17% cửa sổ, tín hiệu đã nguội.",
        "Cảnh báo: Sàn khác (okx) đang dẫn nhịp trước Binance."
      ],
      "invalidation": "Mất bid hỗ trợ dưới 70877.55",
      "entry_style": "Canh hồi về bid và giữ microprice",
      "targets": [
        "TP1: 1 ATR giả lập",
        "TP2: 2 ATR giả lập"
      ],
      "timeframe": "1h",
      "regime_bucket": "NEUTRAL",
      "flow_state": "SHORT_TRAP_RISK__TRAP",
      "matrix_cell": "NEG_INIT__POS_INV",
      "matrix_alias_vi": "Bán gặp hấp thụ mua",
      "tradability_grade": "D",
      "decision_posture": "WAIT",
      "decision_summary_vi": "Chỉ theo dõi, chờ thêm xác nhận từ futures hoặc đa sàn trước khi hành động.",
      "flow_alignment_score": 0.0,
      "ai_brief_vi": "",
      "edge_score": 0.64,
      "edge_confidence": "LOW",
      "pattern_code": "TRAP_SHORT",
      "pattern_phase": "FORMING",
      "sequence_signature": "NEG_POSx1|STABLE|NONE|ABSORBED_OR_TRAP",
      "created_at": "2026-03-26T04:32:11.233000+00:00",
      "updated_at": "2026-03-26T04:32:37.039000+00:00",
      "metadata": {},
      "delta_score": 0,
      "prev_grade": "",
      "grade_changed": false,
      "setup_changed": false,
      "prev_setup": "",
      "window_ts": 1774499832266
    },
    {
      "thesis_id": "7ae8b3d148a48c72",
      "instrument_key": "BINANCE:BTCUSDT:SPOT",
      "setup": "stealth_accumulation",
      "direction": "LONG_BIAS",
      "stage": "INVALIDATED",
      "score": 70.0,
      "confidence": 0.82,
      "coverage": 0.79,
      "why_now": [
        "Delta mua dương: 104231.75",
        "Bid L1 áp đảo: 0.87",
        "Nhịp trade tăng: 5.19/s",
        "Spread còn mỏng: 0.00 bps",
        "Hấp thụ chủ động cao: 108906.12"
      ],
      "conflicts": [
        "Giá khớp trượt dưới microprice",
        "Dòng tiền mới chỉ chiếm 17% cửa sổ, tín hiệu đã nguội.",
        "Cảnh báo: Sàn khác (okx) đang dẫn nhịp trước Binance."
      ],
      "invalidation": "Mất bid hỗ trợ dưới 70877.55",
      "entry_style": "Canh hồi về bid và giữ microprice",
      "targets": [
        "TP1: 1 ATR giả lập",
        "TP2: 2 ATR giả lập"
      ],
      "timeframe": "1h",
      "regime_bucket": "NEUTRAL",
      "flow_state": "LONG_TRAP_RISK",
      "matrix_cell": "POS_INIT__NEG_INV",
      "matrix_alias_vi": "Mua gặp hấp thụ bán",
      "tradability_grade": "D",
      "decision_posture": "WAIT",
      "decision_summary_vi": "Chỉ theo long khi vượt hấp thụ và có xác nhận thêm từ futures/venue lead.",
      "flow_alignment_score": 0.0,
      "ai_brief_vi": "",
      "edge_score": 0.59,
      "edge_confidence": "LOW",
      "pattern_code": "TRAP_LONG",
      "pattern_phase": "FORMING",
      "sequence_signature": "POS_NEGx1|STABLE|NONE|MIXED",
      "created_at": "2026-03-26T04:32:11.233000+00:00",
      "updated_at": "2026-03-26T04:32:37.039000+00:00",
      "metadata": {},
      "delta_score": 0.0,
      "prev_grade": "D",
      "grade_changed": false,
      "setup_changed": false,
      "prev_setup": "stealth_accumulation",
      "window_ts": 1774500131889
    },
    {
      "thesis_id": "7ae8b3d148a48c72",
      "instrument_key": "BINANCE:BTCUSDT:SPOT",
      "setup": "stealth_accumulation",
      "direction": "LONG_BIAS",
      "stage": "INVALIDATED",
      "score": 70.0,
      "confidence": 0.82,
      "coverage": 0.79,
      "why_now": [
        "Delta mua dương: 104231.75",
        "Bid L1 áp đảo: 0.87",
        "Nhịp trade tăng: 5.19/s",
        "Spread còn mỏng: 0.00 bps",
        "Hấp thụ chủ động cao: 108906.12"
      ],
      "conflicts": [
        "Giá khớp trượt dưới microprice",
        "Dòng tiền mới chỉ chiếm 17% cửa sổ, tín hiệu đã nguội.",
        "Cảnh báo: Sàn khác (okx) đang dẫn nhịp trước Binance."
      ],
      "invalidation": "Mất bid hỗ trợ dưới 70877.55",
      "entry_style": "Canh hồi về bid và giữ microprice",
      "targets": [
        "TP1: 1 ATR giả lập",
        "TP2: 2 ATR giả lập"
      ],
      "timeframe": "1h",
      "regime_bucket": "NEUTRAL",
      "flow_state": "SHORT_CONTINUATION",
      "matrix_cell": "NEG_INIT__NEG_INV",
      "matrix_alias_vi": "Thuận pha bán",
      "tradability_grade": "D",
      "decision_posture": "WAIT",
      "decision_summary_vi": "Ưu tiên continuation short khi hồi yếu và ask vẫn ép xuống.",
      "flow_alignment_score": 0.0,
      "ai_brief_vi": "",
      "edge_score": 0.76,
      "edge_confidence": "LOW",
      "pattern_code": "UNCLASSIFIED",
      "pattern_phase": "FORMING",
      "sequence_signature": "NEG_NEGx1|ACCELERATING|NONE|MIXED",
      "created_at": "2026-03-26T04:32:11.233000+00:00",
      "updated_at": "2026-03-26T04:32:37.039000+00:00",
      "metadata": {},
      "delta_score": 0.0,
      "prev_grade": "D",
      "grade_changed": false,
      "setup_changed": false,
      "prev_setup": "stealth_accumulation",
      "window_ts": 1774500433243
    },
    {
      "thesis_id": "7ae8b3d148a48c72",
      "instrument_key": "BINANCE:BTCUSDT:SPOT",
      "setup": "stealth_accumulation",
      "direction": "LONG_BIAS",
      "stage": "INVALIDATED",
      "score": 70.0,
      "confidence": 0.82,
      "coverage": 0.79,
      "why_now": [
        "Delta mua dương: 104231.75",
        "Bid L1 áp đảo: 0.87",
        "Nhịp trade tăng: 5.19/s",
        "Spread còn mỏng: 0.00 bps",
        "Hấp thụ chủ động cao: 108906.12"
      ],
      "conflicts": [
        "Giá khớp trượt dưới microprice",
        "Dòng tiền mới chỉ chiếm 17% cửa sổ, tín hiệu đã nguội.",
        "Cảnh báo: Sàn khác (okx) đang dẫn nhịp trước Binance."
      ],
      "invalidation": "Mất bid hỗ trợ dưới 70877.55",
      "entry_style": "Canh hồi về bid và giữ microprice",
      "targets": [
        "TP1: 1 ATR giả lập",
        "TP2: 2 ATR giả lập"
      ],
      "timeframe": "1h",
      "regime_bucket": "NEUTRAL",
      "flow_state": "PASSIVE_ASK_SUPPLY__TRAP",
      "matrix_cell": "NEUTRAL_INIT__NEG_INV",
      "matrix_alias_vi": "Đè thụ động",
      "tradability_grade": "D",
      "decision_posture": "WAIT",
      "decision_summary_vi": "Chỉ theo dõi, chờ thêm xác nhận từ futures hoặc đa sàn trước khi hành động.",
      "flow_alignment_score": 0.0,
      "ai_brief_vi": "",
      "edge_score": 0.45,
      "edge_confidence": "LOW",
      "pattern_code": "PASSIVE_DISTRIBUTION",
      "pattern_phase": "FORMING",
      "sequence_signature": "NEUTRAL_NEGx1|DECELERATING|NONE|ABSORBED_OR_TRAP",
      "created_at": "2026-03-26T04:32:11.233000+00:00",
      "updated_at": "2026-03-26T04:32:37.039000+00:00",
      "metadata": {},
      "delta_score": 0.0,
      "prev_grade": "D",
      "grade_changed": false,
      "setup_changed": false,
      "prev_setup": "stealth_accumulation",
      "window_ts": 1774500732827
    },
    {
      "thesis_id": "7ae8b3d148a48c72",
      "instrument_key": "BINANCE:BTCUSDT:SPOT",
      "setup": "stealth_accumulation",
      "direction": "LONG_BIAS",
      "stage": "INVALIDATED",
      "score": 70.0,
      "confidence": 0.82,
      "coverage": 0.79,
      "why_now": [
        "Delta mua dương: 104231.75",
        "Bid L1 áp đảo: 0.87",
        "Nhịp trade tăng: 5.19/s",
        "Spread còn mỏng: 0.00 bps",
        "Hấp thụ chủ động cao: 108906.12"
      ],
      "conflicts": [
        "Giá khớp trượt dưới microprice",
        "Dòng tiền mới chỉ chiếm 17% cửa sổ, tín hiệu đã nguội.",
        "Cảnh báo: Sàn khác (okx) đang dẫn nhịp trước Binance."
      ],
      "invalidation": "Mất bid hỗ trợ dưới 70877.55",
      "entry_style": "Canh hồi về bid và giữ microprice",
      "targets": [
        "TP1: 1 ATR giả lập",
        "TP2: 2 ATR giả lập"
      ],
      "timeframe": "1h",
      "regime_bucket": "NEUTRAL",
      "flow_state": "BUY_PRESSURE_BUILDUP__TRAP",
      "matrix_cell": "POS_INIT__NEUTRAL_INV",
      "matrix_alias_vi": "Mua chủ động chưa có đỡ",
      "tradability_grade": "D",
      "decision_posture": "WAIT",
      "decision_summary_vi": "Chỉ theo dõi, chờ thêm xác nhận từ futures hoặc đa sàn trước khi hành động.",
      "flow_alignment_score": 0.0,
      "ai_brief_vi": "",
      "edge_score": 0.45,
      "edge_confidence": "LOW",
      "pattern_code": "BREAKOUT_FORMING_LONG",
      "pattern_phase": "FORMING",
      "sequence_signature": "POS_NEUTRALx1|DECELERATING|NONE|ABSORBED_OR_TRAP",
      "created_at": "2026-03-26T04:32:11.233000+00:00",
      "updated_at": "2026-03-26T04:32:37.039000+00:00",
      "metadata": {},
      "delta_score": 0.0,
      "prev_grade": "D",
      "grade_changed": false,
      "setup_changed": false,
      "prev_setup": "stealth_accumulation",
      "window_ts": 1774501033443
    },
    {
      "thesis_id": "7ae8b3d148a48c72",
      "instrument_key": "BINANCE:BTCUSDT:SPOT",
      "setup": "stealth_accumulation",
      "direction": "LONG_BIAS",
      "stage": "INVALIDATED",
      "score": 70.0,
      "confidence": 0.82,
      "coverage": 0.79,
      "why_now": [
        "Delta mua dương: 104231.75",
        "Bid L1 áp đảo: 0.87",
        "Nhịp trade tăng: 5.19/s",
        "Spread còn mỏng: 0.00 bps",
        "Hấp thụ chủ động cao: 108906.12"
      ],
      "conflicts": [
        "Giá khớp trượt dưới microprice",
        "Dòng tiền mới chỉ chiếm 17% cửa sổ, tín hiệu đã nguội.",
        "Cảnh báo: Sàn khác (okx) đang dẫn nhịp trước Binance."
      ],
      "invalidation": "Mất bid hỗ trợ dưới 70877.55",
      "entry_style": "Canh hồi về bid và giữ microprice",
      "targets": [
        "TP1: 1 ATR giả lập",
        "TP2: 2 ATR giả lập"
      ],
      "timeframe": "1h",
      "regime_bucket": "NEUTRAL",
      "flow_state": "SHORT_TRAP_RISK",
      "matrix_cell": "NEG_INIT__POS_INV",
      "matrix_alias_vi": "Bán gặp hấp thụ mua",
      "tradability_grade": "D",
      "decision_posture": "WAIT",
      "decision_summary_vi": "Ưu tiên chờ failed breakdown hoặc hồi bán lại thay vì đuổi short.",
      "flow_alignment_score": 0.0,
      "ai_brief_vi": "",
      "edge_score": 0.0,
      "edge_confidence": "HIGH",
      "pattern_code": "TRAP_SHORT",
      "pattern_phase": "FORMING",
      "sequence_signature": "NEG_POSx1|STABLE|NONE|MIXED",
      "created_at": "2026-03-26T04:32:11.233000+00:00",
      "updated_at": "2026-03-26T04:32:37.039000+00:00",
      "metadata": {},
      "delta_score": 0.0,
      "prev_grade": "D",
      "grade_changed": false,
      "setup_changed": false,
      "prev_setup": "stealth_accumulation",
      "window_ts": 1774501335350
    },
    {
      "thesis_id": "7ae8b3d148a48c72",
      "instrument_key": "BINANCE:BTCUSDT:SPOT",
      "setup": "stealth_accumulation",
      "direction": "LONG_BIAS",
      "stage": "INVALIDATED",
      "score": 70.0,
      "confidence": 0.82,
      "coverage": 0.79,
      "why_now": [
        "Delta mua dương: 104231.75",
        "Bid L1 áp đảo: 0.87",
        "Nhịp trade tăng: 5.19/s",
        "Spread còn mỏng: 0.00 bps",
        "Hấp thụ chủ động cao: 108906.12"
      ],
      "conflicts": [
        "Giá khớp trượt dưới microprice",
        "Dòng tiền mới chỉ chiếm 17% cửa sổ, tín hiệu đã nguội.",
        "Cảnh báo: Sàn khác (okx) đang dẫn nhịp trước Binance."
      ],
      "invalidation": "Mất bid hỗ trợ dưới 70877.55",
      "entry_style": "Canh hồi về bid và giữ microprice",
      "targets": [
        "TP1: 1 ATR giả lập",
        "TP2: 2 ATR giả lập"
      ],
      "timeframe": "1h",
      "regime_bucket": "NEUTRAL",
      "flow_state": "SELL_PRESSURE_BUILDUP",
      "matrix_cell": "NEG_INIT__NEUTRAL_INV",
      "matrix_alias_vi": "Bán chủ động chưa có đè",
      "tradability_grade": "D",
      "decision_posture": "WAIT",
      "decision_summary_vi": "Chỉ theo dõi, chờ thêm xác nhận từ futures hoặc đa sàn trước khi hành động.",
      "flow_alignment_score": 0.0,
      "ai_brief_vi": "",
      "edge_score": 0.0,
      "edge_confidence": "MEDIUM",
      "pattern_code": "BREAKDOWN_FORMING_SHORT",
      "pattern_phase": "FORMING",
      "sequence_signature": "NEG_NEUTRALx1|DECELERATING|NONE|MIXED",
      "created_at": "2026-03-26T04:32:11.233000+00:00",
      "updated_at": "2026-03-26T04:32:37.039000+00:00",
      "metadata": {},
      "delta_score": 0.0,
      "prev_grade": "D",
      "grade_changed": false,
      "setup_changed": false,
      "prev_setup": "stealth_accumulation",
      "window_ts": 1774501349893
    },
    {
      "thesis_id": "7ae8b3d148a48c72",
      "instrument_key": "BINANCE:BTCUSDT:SPOT",
      "setup": "stealth_accumulation",
      "direction": "LONG_BIAS",
      "stage": "INVALIDATED",
      "score": 70.0,
      "confidence": 0.82,
      "coverage": 0.79,
      "why_now": [
        "Delta mua dương: 104231.75",
        "Bid L1 áp đảo: 0.87",
        "Nhịp trade tăng: 5.19/s",
        "Spread còn mỏng: 0.00 bps",
        "Hấp thụ chủ động cao: 108906.12"
      ],
      "conflicts": [
        "Giá khớp trượt dưới microprice",
        "Dòng tiền mới chỉ chiếm 17% cửa sổ, tín hiệu đã nguội.",
        "Cảnh báo: Sàn khác (okx) đang dẫn nhịp trước Binance."
      ],
      "invalidation": "Mất bid hỗ trợ dưới 70877.55",
      "entry_style": "Canh hồi về bid và giữ microprice",
      "targets": [
        "TP1: 1 ATR giả lập",
        "TP2: 2 ATR giả lập"
      ],
      "timeframe": "1h",
      "regime_bucket": "NEUTRAL",
      "flow_state": "SHORT_TRAP_RISK",
      "matrix_cell": "NEG_INIT__POS_INV",
      "matrix_alias_vi": "Bán gặp hấp thụ mua",
      "tradability_grade": "D",
      "decision_posture": "WAIT",
      "decision_summary_vi": "Chỉ theo dõi, chờ thêm xác nhận từ futures hoặc đa sàn trước khi hành động.",
      "flow_alignment_score": 0.0,
      "ai_brief_vi": "",
      "edge_score": 0.0,
      "edge_confidence": "HIGH",
      "pattern_code": "TRAP_SHORT",
      "pattern_phase": "FORMING",
      "sequence_signature": "NEG_POSx1|STABLE|NONE|MIXED",
      "created_at": "2026-03-26T04:32:11.233000+00:00",
      "updated_at": "2026-03-26T04:32:37.039000+00:00",
      "metadata": {},
      "delta_score": 0.0,
      "prev_grade": "D",
      "grade_changed": false,
      "setup_changed": false,
      "prev_setup": "stealth_accumulation",
      "window_ts": 1774501362562
    },
    {
      "thesis_id": "7ae8b3d148a48c72",
      "instrument_key": "BINANCE:BTCUSDT:SPOT",
      "setup": "stealth_accumulation",
      "direction": "LONG_BIAS",
      "stage": "INVALIDATED",
      "score": 70.0,
      "confidence": 0.82,
      "coverage": 0.79,
      "why_now": [
        "Delta mua dương: 104231.75",
        "Bid L1 áp đảo: 0.87",
        "Nhịp trade tăng: 5.19/s",
        "Spread còn mỏng: 0.00 bps",
        "Hấp thụ chủ động cao: 108906.12"
      ],
      "conflicts": [
        "Giá khớp trượt dưới microprice",
        "Dòng tiền mới chỉ chiếm 17% cửa sổ, tín hiệu đã nguội.",
        "Cảnh báo: Sàn khác (okx) đang dẫn nhịp trước Binance."
      ],
      "invalidation": "Mất bid hỗ trợ dưới 70877.55",
      "entry_style": "Canh hồi về bid và giữ microprice",
      "targets": [
        "TP1: 1 ATR giả lập",
        "TP2: 2 ATR giả lập"
      ],
      "timeframe": "1h",
      "regime_bucket": "NEUTRAL",
      "flow_state": "SELL_PRESSURE_BUILDUP",
      "matrix_cell": "NEG_INIT__NEUTRAL_INV",
      "matrix_alias_vi": "Bán chủ động chưa có đè",
      "tradability_grade": "D",
      "decision_posture": "WAIT",
      "decision_summary_vi": "Chỉ theo dõi, chờ thêm xác nhận từ futures hoặc đa sàn trước khi hành động.",
      "flow_alignment_score": 0.0,
      "ai_brief_vi": "",
      "edge_score": 0.0,
      "edge_confidence": "HIGH",
      "pattern_code": "BREAKDOWN_FORMING_SHORT",
      "pattern_phase": "FORMING",
      "sequence_signature": "NEG_NEUTRALx1|STABLE|NONE|MIXED",
      "created_at": "2026-03-26T04:32:11.233000+00:00",
      "updated_at": "2026-03-26T04:32:37.039000+00:00",
      "metadata": {},
      "delta_score": 0.0,
      "prev_grade": "D",
      "grade_changed": false,
      "setup_changed": false,
      "prev_setup": "stealth_accumulation",
      "window_ts": 1774501375845
    }
  ]
}