[{"snapshot_id": "77bc5e80-9876-435a-9101-90a026131b79", "symbol": "BTCUSDT", "window_start_ts": 1774021504414, "window_end_ts": 1774021505414, "initiative_score": 0.3312239869636416, "initiative_polarity": "NEUTRAL_INIT", "inventory_score": 3.39905827751643e-05, "inventory_polarity": "NEUTRAL_INV", "energy_score": 0.08795964385782823, "energy_state": "COMPRESSION", "response_efficiency_score": 0.0, "response_efficiency_state": "MIXED", "matrix_cell": "NEUTRAL_INIT__NEUTRAL_INV", "micro_conclusion": "UNCERTAIN", "tradability_score": 0.23151266770399115, "delta_quote": 150.149, "cvd_slope": 150.149, "trade_burst": 3.0, "active_thesis_count": 4, "actionable_count": 2, "health_state": "DEGRADED_INPUT", "initiative_strength": 0.3312239869636416, "inventory_strength": 3.39905827751643e-05, "axis_confidence": 0.79, "matrix_alias_vi": "Trung tính", "continuation_bias": "NEUTRAL", "preferred_posture": "Đứng ngoài và chờ cấu trúc rõ hơn.", "tradability_grade": "D", "absorption_score": 97.06492487496479, "imbalance_l1": 0.5813402061855671, "centered_imbalance_l1": 0.1626804123711343, "signed_absorption_score": -0.4902935075125035, "microprice_gap_bps": 2.898550724638738, "spread_bps": 9.995002498750056, "new_thesis_count": 4, "invalidated_count": 0, "resolved_count": 0, "dominant_setups": "[\"stealth_accumulation\", \"breakout_ignition\", \"failed_breakout\"]", "setup_score_map": "{\"stealth_accumulation\": 88.0, \"breakout_ignition\": 80.0, \"failed_breakout\": 38.0, \"distribution\": 28.0}", "futures_delta_available": 0, "futures_delta": 0.0, "oi_delta": 0.0, "oi_state": "STABLE", "basis_bps": 0.0, "funding_rate": 0.0, "spot_futures_relation": "NO_FUTURES_DELTA", "context_quality_score": 0.05, "venue_confirmation_state": "UNCONFIRMED", "leader_venue": "", "lagger_venue": "", "venue_vwap_spread_bps": 0.0, "liquidation_context_available": 0, "liquidation_bias": "UNKNOWN", "liquidation_count": 0, "liquidation_quote": 0.0, "flow_state_code": "NEUTRAL_BALANCE", "forced_flow_state": "NONE", "forced_flow_intensity": 0.0, "inventory_defense_state": "NONE", "liquidation_intensity": 0.0, "transition_ready": 0, "trap_risk": 0.0, "decision_posture": "WAIT", "decision_summary_vi": "Đứng ngoài. Matrix chưa đủ sạch để hành động.", "entry_condition_vi": "N/A", "confirm_needed_vi": "Chờ thêm xác nhận từ futures hoặc đa sàn", "avoid_if_vi": "N/A", "review_tags_json": "{\"flow_state_code\": \"NEUTRAL_BALANCE\", \"matrix_cell\": \"NEUTRAL_INIT__NEUTRAL_INV\", \"continuation_bias\": \"NEUTRAL\", \"spot_futures_relation\": \"NO_FUTURES_DELTA\", \"forced_flow_state\": \"NONE\", \"venue_confirmation_state\": \"UNCONFIRMED\", \"tradability_grade\": \"D\", \"basis_state\": \"BALANCED\", \"inventory_defense_state\": \"NONE\"}", "blind_spot_flags": "[\"THIN_M5_WINDOW\", \"NO_FUTURES_CONTEXT\", \"STALE_FUTURES_CONTEXT\", \"NO_FUTURES_DELTA\", \"NO_LIQUIDATION_FEED\", \"NO_VENUE_CONFIRMATION\"]", "observed_facts": "[\"Delta spot +150\", \"Nhịp 3.00/s\", \"Inventory L1 +16%\", \"Hấp thụ ký hiệu -0.49\", \"Dòng tiền duy trì đều 0.46\"]", "inferred_facts": "[\"Trung tính\", \"Flow state: NEUTRAL_BALANCE\"]", "missing_context": "[\"Chưa có context futures.\", \"Chưa có xác nhận đa sàn.\", \"Chưa có liquidation feed.\"]", "risk_flags": "[\"THIẾU CONTEXT FUTURES\", \"CONTEXT FUTURES CHƯA TƯƠI\", \"THIẾU FUTURES DELTA\"]", "action_plan_vi": "Đứng ngoài. Matrix chưa đủ sạch để hành động.", "invalid_if": "Matrix không còn giữ được hướng hiện tại.", "delta_zscore": 0.0, "aggression_ratio": 0.7419845605892117, "sweep_quote": 0.0, "sweep_buy_quote": 0.0, "sweep_sell_quote": 0.0, "burst_persistence": 0.4559201061526643, "microprice_drift_bps": -0.6327937300871095, "replenishment_bid_score": 220.09600000000003, "replenishment_ask_score": 300.247, "oi_expansion_ratio": 0.0, "futures_aggression_ratio": 0.5, "basis_state": "BALANCED", "leader_confidence": 0.0, "aligned_window_ms": 0}, {"snapshot_id": "03d43364-ad8b-4450-8e13-ff1dd49c72ac", "symbol": "BTCUSDT", "window_start_ts": 1774020433591, "window_end_ts": 1774020434591, "initiative_score": 0.3312239869636416, "initiative_polarity": "NEUTRAL_INIT", "inventory_score": 3.39905827751643e-05, "inventory_polarity": "NEUTRAL_INV", "energy_score": 0.08795964385782823, "energy_state": "COMPRESSION", "response_efficiency_score": 0.0, "response_efficiency_state": "MIXED", "matrix_cell": "NEUTRAL_INIT__NEUTRAL_INV", "micro_conclusion": "UNCERTAIN", "tradability_score": 0.23151266770399115, "delta_quote": 150.149, "cvd_slope": 150.149, "trade_burst": 3.0, "active_thesis_count": 4, "actionable_count": 2, "health_state": "DEGRADED_INPUT", "initiative_strength": 0.3312239869636416, "inventory_strength": 3.39905827751643e-05, "axis_confidence": 0.79, "matrix_alias_vi": "Trung tính", "continuation_bias": "NEUTRAL", "preferred_posture": "Đứng ngoài và chờ cấu trúc rõ hơn.", "tradability_grade": "D", "absorption_score": 97.06492487496479, "imbalance_l1": 0.5813402061855671, "centered_imbalance_l1": 0.1626804123711343, "signed_absorption_score": -0.4902935075125035, "microprice_gap_bps": 2.898550724638738, "spread_bps": 9.995002498750056, "new_thesis_count": 4, "invalidated_count": 0, "resolved_count": 0, "dominant_setups": "[\"stealth_accumulation\", \"breakout_ignition\", \"failed_breakout\"]", "setup_score_map": "{\"stealth_accumulation\": 88.0, \"breakout_ignition\": 80.0, \"failed_breakout\": 38.0, \"distribution\": 28.0}", "futures_delta_available": 0, "futures_delta": 0.0, "oi_delta": 0.0, "oi_state": "STABLE", "basis_bps": 0.0, "funding_rate": 0.0, "spot_futures_relation": "NO_FUTURES_DELTA", "context_quality_score": 0.05, "venue_confirmation_state": "UNCONFIRMED", "leader_venue": "", "lagger_venue": "", "venue_vwap_spread_bps": 0.0, "liquidation_context_available": 0, "liquidation_bias": "UNKNOWN", "liquidation_count": 0, "liquidation_quote": 0.0, "flow_state_code": "NEUTRAL_BALANCE", "forced_flow_state": "NONE", "forced_flow_intensity": 0.0, "inventory_defense_state": "NONE", "liquidation_intensity": 0.0, "transition_ready": 0, "trap_risk": 0.0, "decision_posture": "WAIT", "decision_summary_vi": "Đứng ngoài. Matrix chưa đủ sạch để hành động.", "entry_condition_vi": "N/A", "confirm_needed_vi": "Chờ thêm xác nhận từ futures hoặc đa sàn", "avoid_if_vi": "N/A", "review_tags_json": "{\"flow_state_code\": \"NEUTRAL_BALANCE\", \"matrix_cell\": \"NEUTRAL_INIT__NEUTRAL_INV\", \"continuation_bias\": \"NEUTRAL\", \"spot_futures_relation\": \"NO_FUTURES_DELTA\", \"forced_flow_state\": \"NONE\", \"venue_confirmation_state\": \"UNCONFIRMED\", \"tradability_grade\": \"D\", \"basis_state\": \"BALANCED\", \"inventory_defense_state\": \"NONE\"}", "blind_spot_flags": "[\"THIN_M5_WINDOW\", \"NO_FUTURES_CONTEXT\", \"STALE_FUTURES_CONTEXT\", \"NO_FUTURES_DELTA\", \"NO_LIQUIDATION_FEED\", \"NO_VENUE_CONFIRMATION\"]", "observed_facts": "[\"Delta spot +150\", \"Nhịp 3.00/s\", \"Inventory L1 +16%\", \"Hấp thụ ký hiệu -0.49\", \"Dòng tiền duy trì đều 0.46\"]", "inferred_facts": "[\"Trung tính\", \"Flow state: NEUTRAL_BALANCE\"]", "missing_context": "[\"Chưa có context futures.\", \"Chưa có xác nhận đa sàn.\", \"Chưa có liquidation feed.\"]", "risk_flags": "[\"THIẾU CONTEXT FUTURES\", \"CONTEXT FUTURES CHƯA TƯƠI\", \"THIẾU FUTURES DELTA\"]", "action_plan_vi": "Đứng ngoài. Matrix chưa đủ sạch để hành động.", "invalid_if": "Matrix không còn giữ được hướng hiện tại.", "delta_zscore": 0.0, "aggression_ratio": 0.7419845605892117, "sweep_quote": 0.0, "sweep_buy_quote": 0.0, "sweep_sell_quote": 0.0, "burst_persistence": 0.4559201061526643, "microprice_drift_bps": -0.6327937300871095, "replenishment_bid_score": 220.09600000000003, "replenishment_ask_score": 300.247, "oi_expansion_ratio": 0.0, "futures_aggression_ratio": 0.5, "basis_state": "BALANCED", "leader_confidence": 0.0, "aligned_window_ms": 0}, {"snapshot_id": "9749eda5-8b25-4838-9ee1-01daa191e917", "symbol": "BTCUSDT", "window_start_ts": 1774020202213, "window_end_ts": 1774020203213, "initiative_score": 0.3312239869636416, "initiative_polarity": "NEUTRAL_INIT", "inventory_score": 3.39905827751643e-05, "inventory_polarity": "NEUTRAL_INV", "energy_score": 0.08795964385782823, "energy_state": "COMPRESSION", "response_efficiency_score": 0.0, "response_efficiency_state": "MIXED", "matrix_cell": "NEUTRAL_INIT__NEUTRAL_INV", "micro_conclusion": "UNCERTAIN", "tradability_score": 0.23151266770399115, "delta_quote": 150.149, "cvd_slope": 150.149, "trade_burst": 3.0, "active_thesis_count": 4, "actionable_count": 2, "health_state": "DEGRADED_INPUT", "initiative_strength": 0.3312239869636416, "inventory_strength": 3.39905827751643e-05, "axis_confidence": 0.79, "matrix_alias_vi": "Trung tính", "continuation_bias": "NEUTRAL", "preferred_posture": "Đứng ngoài và chờ cấu trúc rõ hơn.", "tradability_grade": "D", "absorption_score": 97.06492487496479, "imbalance_l1": 0.5813402061855671, "centered_imbalance_l1": 0.1626804123711343, "signed_absorption_score": -0.4902935075125035, "microprice_gap_bps": 2.898550724638738, "spread_bps": 9.995002498750056, "new_thesis_count": 4, "invalidated_count": 0, "resolved_count": 0, "dominant_setups": "[\"stealth_accumulation\", \"breakout_ignition\", \"failed_breakout\"]", "setup_score_map": "{\"stealth_accumulation\": 88.0, \"breakout_ignition\": 80.0, \"failed_breakout\": 38.0, \"distribution\": 28.0}", "futures_delta_available": 0, "futures_delta": 0.0, "oi_delta": 0.0, "oi_state": "STABLE", "basis_bps": 0.0, "funding_rate": 0.0, "spot_futures_relation": "NO_FUTURES_DELTA", "context_quality_score": 0.05, "venue_confirmation_state": "UNCONFIRMED", "leader_venue": "", "lagger_venue": "", "venue_vwap_spread_bps": 0.0, "liquidation_context_available": 0, "liquidation_bias": "UNKNOWN", "liquidation_count": 0, "liquidation_quote": 0.0, "flow_state_code": "NEUTRAL_BALANCE", "forced_flow_state": "NONE", "forced_flow_intensity": 0.0, "inventory_defense_state": "NONE", "liquidation_intensity": 0.0, "transition_ready": 0, "trap_risk": 0.0, "decision_posture": "WAIT", "decision_summary_vi": "Đứng ngoài. Matrix chưa đủ sạch để hành động.", "entry_condition_vi": "N/A", "confirm_needed_vi": "Chờ thêm xác nhận từ futures hoặc đa sàn", "avoid_if_vi": "N/A", "review_tags_json": "{\"flow_state_code\": \"NEUTRAL_BALANCE\", \"matrix_cell\": \"NEUTRAL_INIT__NEUTRAL_INV\", \"continuation_bias\": \"NEUTRAL\", \"spot_futures_relation\": \"NO_FUTURES_DELTA\", \"forced_flow_state\": \"NONE\", \"venue_confirmation_state\": \"UNCONFIRMED\", \"tradability_grade\": \"D\", \"basis_state\": \"BALANCED\", \"inventory_defense_state\": \"NONE\"}", "blind_spot_flags": "[\"THIN_M5_WINDOW\", \"NO_FUTURES_CONTEXT\", \"STALE_FUTURES_CONTEXT\", \"NO_FUTURES_DELTA\", \"NO_LIQUIDATION_FEED\", \"NO_VENUE_CONFIRMATION\"]", "observed_facts": "[\"Delta spot +150\", \"Nhịp 3.00/s\", \"Inventory L1 +16%\", \"Hấp thụ ký hiệu -0.49\", \"Dòng tiền duy trì đều 0.46\"]", "inferred_facts": "[\"Trung tính\", \"Flow state: NEUTRAL_BALANCE\"]", "missing_context": "[\"Chưa có context futures.\", \"Chưa có xác nhận đa sàn.\", \"Chưa có liquidation feed.\"]", "risk_flags": "[\"THIẾU CONTEXT FUTURES\", \"CONTEXT FUTURES CHƯA TƯƠI\", \"THIẾU FUTURES DELTA\"]", "action_plan_vi": "Đứng ngoài. Matrix chưa đủ sạch để hành động.", "invalid_if": "Matrix không còn giữ được hướng hiện tại.", "delta_zscore": 0.0, "aggression_ratio": 0.7419845605892117, "sweep_quote": 0.0, "sweep_buy_quote": 0.0, "sweep_sell_quote": 0.0, "burst_persistence": 0.4559201061526643, "microprice_drift_bps": -0.6327937300871095, "replenishment_bid_score": 220.09600000000003, "replenishment_ask_score": 300.247, "oi_expansion_ratio": 0.0, "futures_aggression_ratio": 0.5, "basis_state": "BALANCED", "leader_confidence": 0.0, "aligned_window_ms": 0}, {"snapshot_id": "9e20df39-e9a8-457e-93c2-76291b9b06fe", "symbol": "BTCUSDT", "window_start_ts": 1773983552965, "window_end_ts": 1773983553965, "initiative_score": 0.38959810411784235, "initiative_polarity": "POS_INIT", "inventory_score": 0.06439569528682816, "inventory_polarity": "NEUTRAL_INV", "energy_score": 0.10873995147611502, "energy_state": "COMPRESSION", "response_efficiency_score": 0.0, "response_efficiency_state": "MIXED", "matrix_cell": "POS_INIT__NEUTRAL_INV", "micro_conclusion": "INITIATIVE_DRIVEN", "tradability_score": 0.22699689970233525, "delta_quote": 150.149, "cvd_slope": 150.149, "trade_burst": 3.0, "active_thesis_count": 0, "actionable_count": 0, "health_state": "HEALTHY", "initiative_strength": null, "inventory_strength": null, "axis_confidence": null, "matrix_alias_vi": null, "continuation_bias": null, "preferred_posture": null, "tradability_grade": null, "absorption_score": null, "imbalance_l1": null, "centered_imbalance_l1": null, "signed_absorption_score": null, "microprice_gap_bps": null, "spread_bps": null, "new_thesis_count": null, "invalidated_count": null, "resolved_count": null, "dominant_setups": null, "setup_score_map": null, "futures_delta_available": null, "futures_delta": null, "oi_delta": null, "oi_state": null, "basis_bps": null, "funding_rate": null, "spot_futures_relation": null, "context_quality_score": null, "venue_confirmation_state": null, "leader_venue": null, "lagger_venue": null, "venue_vwap_spread_bps": null, "liquidation_context_available": null, "liquidation_bias": null, "liquidation_count": null, "liquidation_quote": null, "flow_state_code": "NEUTRAL", "forced_flow_state": "NONE", "forced_flow_intensity": 0.0, "inventory_defense_state": "NONE", "liquidation_intensity": 0.0, "transition_ready": 0, "trap_risk": 0.0, "decision_posture": "WAIT", "decision_summary_vi": null, "entry_condition_vi": null, "confirm_needed_vi": null, "avoid_if_vi": null, "review_tags_json": null, "blind_spot_flags": null, "observed_facts": null, "inferred_facts": null, "missing_context": null, "risk_flags": null, "action_plan_vi": null, "invalid_if": null, "delta_zscore": 0.0, "aggression_ratio": 0.5, "sweep_quote": 0.0, "sweep_buy_quote": 0.0, "sweep_sell_quote": 0.0, "burst_persistence": 0.0, "microprice_drift_bps": 0.0, "replenishment_bid_score": 0.0, "replenishment_ask_score": 0.0, "oi_expansion_ratio": 0.0, "futures_aggression_ratio": 0.5, "basis_state": "BALANCED", "leader_confidence": 0.0, "aligned_window_ms": 0}, {"snapshot_id": "55a5f5ab-92a2-4534-acd8-6815a314b81c", "symbol": "BTCUSDT", "window_start_ts": 1773969640708, "window_end_ts": 1773969641708, "initiative_score": 0.38959810411784235, "initiative_polarity": "POS_INIT", "inventory_score": 0.06439569528682816, "inventory_polarity": "NEUTRAL_INV", "energy_score": 0.10873995147611502, "energy_state": "COMPRESSION", "response_efficiency_score": 0.0, "response_efficiency_state": "MIXED", "matrix_cell": "POS_INIT__NEUTRAL_INV", "micro_conclusion": "INITIATIVE_DRIVEN", "tradability_score": 0.22699689970233525, "delta_quote": 150.149, "cvd_slope": 150.149, "trade_burst": 3.0, "active_thesis_count": 0, "actionable_count": 0, "health_state": "HEALTHY", "initiative_strength": null, "inventory_strength": null, "axis_confidence": null, "matrix_alias_vi": null, "continuation_bias": null, "preferred_posture": null, "tradability_grade": null, "absorption_score": null, "imbalance_l1": null, "centered_imbalance_l1": null, "signed_absorption_score": null, "microprice_gap_bps": null, "spread_bps": null, "new_thesis_count": null, "invalidated_count": null, "resolved_count": null, "dominant_setups": null, "setup_score_map": null, "futures_delta_available": null, "futures_delta": null, "oi_delta": null, "oi_state": null, "basis_bps": null, "funding_rate": null, "spot_futures_relation": null, "context_quality_score": null, "venue_confirmation_state": null, "leader_venue": null, "lagger_venue": null, "venue_vwap_spread_bps": null, "liquidation_context_available": null, "liquidation_bias": null, "liquidation_count": null, "liquidation_quote": null, "flow_state_code": "NEUTRAL", "forced_flow_state": "NONE", "forced_flow_intensity": 0.0, "inventory_defense_state": "NONE", "liquidation_intensity": 0.0, "transition_ready": 0, "trap_risk": 0.0, "decision_posture": "WAIT", "decision_summary_vi": null, "entry_condition_vi": null, "confirm_needed_vi": null, "avoid_if_vi": null, "review_tags_json": null, "blind_spot_flags": null, "observed_facts": null, "inferred_facts": null, "missing_context": null, "risk_flags": null, "action_plan_vi": null, "invalid_if": null, "delta_zscore": 0.0, "aggression_ratio": 0.5, "sweep_quote": 0.0, "sweep_buy_quote": 0.0, "sweep_sell_quote": 0.0, "burst_persistence": 0.0, "microprice_drift_bps": 0.0, "replenishment_bid_score": 0.0, "replenishment_ask_score": 0.0, "oi_expansion_ratio": 0.0, "futures_aggression_ratio": 0.5, "basis_state": "BALANCED", "leader_confidence": 0.0, "aligned_window_ms": 0}, {"snapshot_id": "1b884481-0106-4e16-8524-71a79c64ecd5", "symbol": "BTCUSDT", "window_start_ts": 1773966559439, "window_end_ts": 1773966560439, "initiative_score": 0.38959810411784235, "initiative_polarity": "POS_INIT", "inventory_score": 0.06439569528682816, "inventory_polarity": "NEUTRAL_INV", "energy_score": 0.10873995147611502, "energy_state": "COMPRESSION", "response_efficiency_score": 0.0, "response_efficiency_state": "MIXED", "matrix_cell": "POS_INIT__NEUTRAL_INV", "micro_conclusion": "INITIATIVE_DRIVEN", "tradability_score": 0.22699689970233525, "delta_quote": 150.149, "cvd_slope": 150.149, "trade_burst": 3.0, "active_thesis_count": 0, "actionable_count": 0, "health_state": "HEALTHY", "initiative_strength": null, "inventory_strength": null, "axis_confidence": null, "matrix_alias_vi": null, "continuation_bias": null, "preferred_posture": null, "tradability_grade": null, "absorption_score": null, "imbalance_l1": null, "centered_imbalance_l1": null, "signed_absorption_score": null, "microprice_gap_bps": null, "spread_bps": null, "new_thesis_count": null, "invalidated_count": null, "resolved_count": null, "dominant_setups": null, "setup_score_map": null, "futures_delta_available": null, "futures_delta": null, "oi_delta": null, "oi_state": null, "basis_bps": null, "funding_rate": null, "spot_futures_relation": null, "context_quality_score": null, "venue_confirmation_state": null, "leader_venue": null, "lagger_venue": null, "venue_vwap_spread_bps": null, "liquidation_context_available": null, "liquidation_bias": null, "liquidation_count": null, "liquidation_quote": null, "flow_state_code": "NEUTRAL", "forced_flow_state": "NONE", "forced_flow_intensity": 0.0, "inventory_defense_state": "NONE", "liquidation_intensity": 0.0, "transition_ready": 0, "trap_risk": 0.0, "decision_posture": "WAIT", "decision_summary_vi": null, "entry_condition_vi": null, "confirm_needed_vi": null, "avoid_if_vi": null, "review_tags_json": null, "blind_spot_flags": null, "observed_facts": null, "inferred_facts": null, "missing_context": null, "risk_flags": null, "action_plan_vi": null, "invalid_if": null, "delta_zscore": 0.0, "aggression_ratio": 0.5, "sweep_quote": 0.0, "sweep_buy_quote": 0.0, "sweep_sell_quote": 0.0, "burst_persistence": 0.0, "microprice_drift_bps": 0.0, "replenishment_bid_score": 0.0, "replenishment_ask_score": 0.0, "oi_expansion_ratio": 0.0, "futures_aggression_ratio": 0.5, "basis_state": "BALANCED", "leader_confidence": 0.0, "aligned_window_ms": 0}, {"snapshot_id": "7d582d1e-84aa-414e-b9df-01fdffc3e406", "symbol": "BTCUSDT", "window_start_ts": 1773966332356, "window_end_ts": 1773966333356, "initiative_score": 0.38959810411784235, "initiative_polarity": "POS_INIT", "inventory_score": 0.06439569528682816, "inventory_polarity": "NEUTRAL_INV", "energy_score": 0.10873995147611502, "energy_state": "COMPRESSION", "response_efficiency_score": 0.0, "response_efficiency_state": "MIXED", "matrix_cell": "POS_INIT__NEUTRAL_INV", "micro_conclusion": "INITIATIVE_DRIVEN", "tradability_score": 0.22699689970233525, "delta_quote": 150.149, "cvd_slope": 150.149, "trade_burst": 3.0, "active_thesis_count": 0, "actionable_count": 0, "health_state": "HEALTHY", "initiative_strength": null, "inventory_strength": null, "axis_confidence": null, "matrix_alias_vi": null, "continuation_bias": null, "preferred_posture": null, "tradability_grade": null, "absorption_score": null, "imbalance_l1": null, "centered_imbalance_l1": null, "signed_absorption_score": null, "microprice_gap_bps": null, "spread_bps": null, "new_thesis_count": null, "invalidated_count": null, "resolved_count": null, "dominant_setups": null, "setup_score_map": null, "futures_delta_available": null, "futures_delta": null, "oi_delta": null, "oi_state": null, "basis_bps": null, "funding_rate": null, "spot_futures_relation": null, "context_quality_score": null, "venue_confirmation_state": null, "leader_venue": null, "lagger_venue": null, "venue_vwap_spread_bps": null, "liquidation_context_available": null, "liquidation_bias": null, "liquidation_count": null, "liquidation_quote": null, "flow_state_code": "NEUTRAL", "forced_flow_state": "NONE", "forced_flow_intensity": 0.0, "inventory_defense_state": "NONE", "liquidation_intensity": 0.0, "transition_ready": 0, "trap_risk": 0.0, "decision_posture": "WAIT", "decision_summary_vi": null, "entry_condition_vi": null, "confirm_needed_vi": null, "avoid_if_vi": null, "review_tags_json": null, "blind_spot_flags": null, "observed_facts": null, "inferred_facts": null, "missing_context": null, "risk_flags": null, "action_plan_vi": null, "invalid_if": null, "delta_zscore": 0.0, "aggression_ratio": 0.5, "sweep_quote": 0.0, "sweep_buy_quote": 0.0, "sweep_sell_quote": 0.0, "burst_persistence": 0.0, "microprice_drift_bps": 0.0, "replenishment_bid_score": 0.0, "replenishment_ask_score": 0.0, "oi_expansion_ratio": 0.0, "futures_aggression_ratio": 0.5, "basis_state": "BALANCED", "leader_confidence": 0.0, "aligned_window_ms": 0}]